picolynx/__init__.py
picolynx/__main__.py
picolynx/app.tcss
picolynx/commands/__init__.py
picolynx/commands/_commands.py
picolynx/components/__init__.py
picolynx/components/_components.py
picolynx/enumerations/__init__.py
picolynx/enumerations/_enumerations.py
picolynx/exceptions/__init__.py
picolynx/exceptions/_exceptions.py
picolynx/messages/__init__.py
picolynx/messages/_messages.py
picolynx/structures/__init__.py
picolynx/structures/_concrete.py
picolynx/structures/_types.py
picolynx/themes/__init__.py
picolynx/themes/_themes.py
picolynx/utility/__init__.py
picolynx/utility/_utility.py
picolynx-0.1.1.dist-info/METADATA
picolynx-0.1.1.dist-info/WHEEL
picolynx-0.1.1.dist-info/entry_points.txt
picolynx-0.1.1.dist-info/licenses/LICENSE.md
picolynx-0.1.1.dist-info/RECORD
