Metadata-Version: 2.4
Name: picolynx
Version: 0.1.1
Summary: Auto-attach microcontrollers to WSL.
Project-URL: Repository, https://github.com/andyrids/picolynx
Project-URL: Issues, https://github.com/andyrids/picolynx/-/issues
Author-email: Andrew Ridyard <andyrids.uncapped698@passmail.net>
Maintainer-email: Andrew Ridyard <andyrids.uncapped698@passmail.net>
License-Expression: GPL-3.0-or-later
License-File: LICENSE.md
Keywords: microcontroller,rpi,textual,tui,usbipd-win,wsl
Classifier: Development Status :: 4 - Beta
Classifier: Intended Audience :: Developers
Classifier: License :: OSI Approved :: GNU General Public License v3 or later (GPLv3+)
Classifier: Natural Language :: English
Classifier: Operating System :: Microsoft :: Windows
Classifier: Programming Language :: Python :: 3 :: Only
Classifier: Programming Language :: Python :: 3.10
Classifier: Programming Language :: Python :: 3.11
Classifier: Programming Language :: Python :: 3.12
Classifier: Programming Language :: Python :: 3.13
Classifier: Topic :: Software Development :: Embedded Systems
Classifier: Topic :: Software Development :: Libraries :: Python Modules
Classifier: Topic :: System :: Hardware :: Universal Serial Bus (USB)
Classifier: Topic :: System :: Monitoring
Requires-Python: >=3.10
Requires-Dist: pydantic>=2.11.9
Requires-Dist: pyserial>=3.5
Requires-Dist: pywin32>=311; sys_platform == 'win32'
Requires-Dist: textual>=5.3.0
